outline_backup_tool/__init__.py
outline_backup_tool/backup.py
outline_backup_tool-0.1.0.dist-info/licenses/LICENSE
outline_backup_tool-0.1.0.dist-info/METADATA
outline_backup_tool-0.1.0.dist-info/WHEEL
outline_backup_tool-0.1.0.dist-info/entry_points.txt
outline_backup_tool-0.1.0.dist-info/top_level.txt
outline_backup_tool-0.1.0.dist-info/RECORD
