Metadata-Version: 2.4
Name: outline-backup-tool
Version: 0.1.0
Summary: 一个用于备份 Outline Wiki 实例的 Python 工具
Home-page: https://github.com/bestbugwriter/outline-backup-tool
Author: lanpangzi
Author-email: yywfqq@live.com
License: MIT
Project-URL: Bug Tracker, https://github.com/bestbugwriter/outline-backup-tool/issues
Classifier: Development Status :: 4 - Beta
Classifier: Intended Audience :: System Administrators
Classifier: Operating System :: OS Independent
Classifier: Programming Language :: Python :: 3
Classifier: Programming Language :: Python :: 3.7
Classifier: Programming Language :: Python :: 3.8
Classifier: Programming Language :: Python :: 3.9
Classifier: Programming Language :: Python :: 3.10
Classifier: Programming Language :: Python :: 3.11
Classifier: Topic :: System :: Archiving :: Backup
Classifier: Topic :: Utilities
Requires-Python: >=3.7
License-File: LICENSE
Requires-Dist: requests>=2.25.0
Dynamic: author
Dynamic: author-email
Dynamic: classifier
Dynamic: description
Dynamic: description-content-type
Dynamic: home-page
Dynamic: license
Dynamic: license-file
Dynamic: project-url
Dynamic: requires-dist
Dynamic: requires-python
Dynamic: summary
